task_automator/__init__.py
task_automator/automator.py
task_automator/examples/__init__.py
task_automator/examples/automation_tree.py
task_automator/examples/automations.py
task_automator/IO/__init__.py
task_automator/IO/directory.py
task_automator/IO/file.py
task_automator/utils/__init__.py
task_automator/utils/github_utils.py
task_automator/utils/web_utils.py
task_automator-0.2.3.dist-info/LICENSE
task_automator-0.2.3.dist-info/METADATA
task_automator-0.2.3.dist-info/WHEEL
task_automator-0.2.3.dist-info/RECORD
