Metadata-Version: 2.3
Name: task-automator
Version: 0.2.3
Summary: Task-Automator is a modern Python framework for building declarative command-line interfaces with nested subcommands, designed for automation workflows and build systems.
License: BSD-3-Clause
Author: Martin Urban
Author-email: martin.urban@studmail.w-hs.de
Requires-Python: >=3.10
Classifier: License :: OSI Approved :: BSD License
Classifier: Programming Language :: Python :: 3
Classifier: Programming Language :: Python :: 3.10
Classifier: Programming Language :: Python :: 3.11
Classifier: Programming Language :: Python :: 3.12
Classifier: Programming Language :: Python :: 3.13
Project-URL: Homepage, https://github.com/urban233/task-automator
Project-URL: Repository, https://github.com/urban233/task-automator
